colvar_toolkit-0.2.0.dist-info/licenses/LICENSE
cvtoolkit/__init__.py
cvtoolkit/colvar.py
tests/helpers.py
tests/test_append.py
tests/test_colvar.py
tests/test_magic_functions.py
colvar_toolkit-0.2.0.dist-info/METADATA
colvar_toolkit-0.2.0.dist-info/WHEEL
colvar_toolkit-0.2.0.dist-info/top_level.txt
colvar_toolkit-0.2.0.dist-info/RECORD
