Metadata-Version: 2.4
Name: colvar-toolkit
Version: 0.2.0
Summary: A Python library for PLUMED-style colvar files
Author-email: Da Teng <tengda1997@gmail.com>
Maintainer-email: Da Teng <tengda1997@gmail.com>
License: MIT license
Project-URL: bugs, https://github.com/k9cdt/colvar/issues
Project-URL: homepage, https://github.com/k9cdt/colvar
Classifier: Intended Audience :: Science/Research
Classifier: License :: OSI Approved :: MIT License
Classifier: Programming Language :: Python
Requires-Python: >=3.10
License-File: LICENSE
Requires-Dist: numpy
Provides-Extra: dev
Requires-Dist: pytest; extra == "dev"
Requires-Dist: ruff; extra == "dev"
Dynamic: license-file
